Workbook

Sheet Lisez-moi
A1: Impact de la hausse des carburants 2026 sur le tertiaire marchand (France)
A3: Question : combien la hausse du gazole coûte-t-elle aux entreprises du tertiaire marchand, branche par branche ?
A5: Comment lire ce classeur
A6: • Paramètres : prix du gazole, indice des prix, scénarios. Les cellules en bleu sont des données saisies ; modifiez-les pour tester d'autres prix.
A7: • Données2019 : achats de produits pétroliers, production, valeur ajoutée et EBE par branche (Eurostat, France, 2019, M€).
A8: • Calculs : les trois indicateurs par groupe de branches, entièrement en formules.
A9: • Prix : prix moyens mensuels du gazole et du SP95-E10 (INSEE), janv. 2022 – août 2026.
A11: Méthode
A12: 1. Achats de carburant 2019 ajustés aux prix relatifs 2025 : C = achats 2019 × k, avec k = (prix gazole 2025 / 2019) ÷ (IPCH 2025 / 2019).
A13: 2. Surcoût : ΔC = C × g, où g est la hausse du gazole par rapport à la moyenne 2025 (scénario A : moyenne mars-août 2026 ; B : 23 septembre 2026).
A14: 3. Poids dans les coûts = C × (1 + g) ÷ (Production − EBE + ΔC).
A15: 4. Perte de taux de marge = EBE ÷ VA − (EBE − ΔC) ÷ (VA − ΔC), en points.
... A31: Analyse et calculs : Mikael Tamimy, septembre 2026.

Sheet Paramètres
A1: Paramètres
A3: Paramètre | B3: Valeur | C3: Unité | D3: Source
A4: Prix du gazole 2019 (moyenne annuelle) | B4: 1.44 | C4: €/L TTC | D4: INSEE, série 010533883
A5: Prix du gazole 2025 (moyenne annuelle) — référence | B5: 1.64 | C5: €/L TTC | D5: INSEE, série 010533883
A6: IPCH 2019 (moyenne annuelle) | B6: 104.95 | C6: indice | D6: Eurostat, prc_hicp_aind, CP00, France
A7: IPCH 2025 (moyenne annuelle) | B7: 124.43 | C7: indice | D7: Eurostat, prc_hicp_aind, CP00, France
A8: Facteur k (passage de la structure 2019 à 2025) | B8: =(B5/B4)/(B7/B6) -> 0.96059141 | C8: — | D8: Calcul
A9: Prix scénario A : moyenne mars-août 2026 | B9: =AVERAGE(Prix!B52:B57) -> 2.1133333 | C9: €/L TTC | D9: Calcul sur l'onglet Prix
A10: Prix scénario B : 23 septembre 2026 | B10: 2.402 | C10: €/L TTC | D10: prix-carburant.eu, moyenne nationale au 23/09/2026
A11: Hausse scénario A (g) | B11: =B9/B5-1 -> 0.28861789 | C11: % | D11: Calcul
A12: Hausse scénario B (g) | B12: =B10/B5-1 -> 0.46463415 | C12: % | D12: Calcul
A14: Cellules bleues : données saisies (modifiables). Cellules noires : formules. Fond jaune : leviers des scénarios.

Sheet Données2019
A1: Code NACE | B1: Branche | C1: Groupe | D1: Transport | E1: Achats de produits pétroliers (M€) | F1: Production (M€) | G1: Valeur ajoutée (M€) | H1: EBE + revenu mixte (M€)
A2: H49 | B2: Transports terrestres et par conduites | C2: Transports terrestres | D2: oui | E2: 7838.25 | F2: 99127 | G2: 47039.27 | H2: 15602.27
A3: H50 | B3: Transports par eau | C3: Transport par eau | D3: oui | E3: 2156.35 | F3: 16970 | G3: 735.57 | H3: -193.43
A4: H51 | B4: Transports aériens | C4: Transport aérien | D4: oui | E4: 4933.4 | F4: 21133 | G4: 7726.46 | H4: 2507.46
A5: H52 | B5: Entreposage et services auxiliaires des transports | C5: Entreposage et services auxiliaires des transports | D5: oui | E5: 983.37 | F5: 74866 | G5: 36057.32 | H5: 16232.32
A6: H53 | B6: Activités de poste et de courrier | C6: Poste et courrier | D6: oui | E6: 100.64 | F6: 12395 | G6: 7777.25 | H6: 346.25
A7: G45 | B7: Commerce et réparation d'automobiles | C7: Commerce et réparation automobile | D7: non | E7: 346.54 | F7: 56242 | G7: 33194.78 | H7: 11328.78
A8: G46 | B8: Commerce de gros | C8: Commerce de gros | D8: non | E8: 3856.45 | F8: 238341 | G8: 102182.45 | H8: 37493.45
A9: G47 | B9: Commerce de détail | C9: Commerce de détail | D9: non | E9: 1309.57 | F9: 161294.17 | G9: 89566.63 | H9: 26883.63
A10: I | B10: Hébergement et restauration | C10: Hébergement-restauration | D10: non | E10: 240.19 | F10: 121745 | G10: 63075.15 | H10: 23226.15
A11: J58 | B11: Édition | C11: Information-communication | D11: non | E11: 68.77 | F11: 29366 | G11: 15233.03 | H11: 5848.03
A12: J59_60 | B12: Production audiovisuelle et diffusion | C12: Information-communication | D12: non | E12: 327.16 | F12: 28525 | G12: 12281.83 | H12: 5754.83
A13: J61 | B13: Télécommunications | C13: Information-communication | D13: non | E13: 380.36 | F13: 56075 | G13: 24970.21 | H13: 15248.21
... A31: S96 | B31: Autres services personnels | C31: Autres services aux ménages | D31: non | E31: 93.33 | F31: 18709 | G31: 12387.95 | H31: 6143.95
A33: Source : Eurostat, naio_10_cp16, use table at purchasers' prices, France, 2019, M€, stk_flow=TOTAL. Produit CPA_C19 (coke et produits pétroliers raffinés), P1, B1G, B2A3G.

Sheet Calculs
A1: Calculs par groupe de branches
A2: Hypothèse : aucune répercussion sur les prix de vente. Scénario A = moyenne mars-août 2026 ; B = prix du 23 septembre 2026.
A4: Groupe de branches | B4: Transport | C4: Carburant 2019 (M€) | D4: Production (M€) | E4: Valeur ajoutée (M€) | F4: EBE (M€) | G4: Carburant base 2025 (M€) | H4: Coûts de production (M€) | I4: Taux de marge avant choc | J4: Poids du carburant 2025 | K4: Poids du carburant A | L4: Poids du carburant B | M4: Points de marge perdus A | N4: Points de marge perdus B | O4: Part de l'EBE absorbée A | P4: Part de l'EBE absorbée B | Q4: Surcoût annuel A (Md€) | R4: Surcoût annuel B (Md€)
A5: Transports terrestres | B5: =INDEX(Données2019!$D$2:$D$31,MATCH(A5,Données2019!$C$2:$C$31,0)) -> oui | C5: =SUMIFS(Données2019!$E$2:$E$31,Données2019!$C$2:$C$31,$A5) -> 7838.25 | D5: =SUMIFS(Données2019!$F$2:$F$31,Données2019!$C$2:$C$31,$A5) -> 99127 | E5: =SUMIFS(Données2019!$G$2:$G$31,Données2019!$C$2:$C$31,$A5) -> 47039.27 | F5: =SUMIFS(Données2019!$H$2:$H$31,Données2019!$C$2:$C$31,$A5) -> 15602.27 | G5: =C5*Paramètres!$B$8 -> 7529.3556 | H5: =D5-F5 -> 83524.73 | I5: =F5/E5 -> 0.33168606 | J5: =G5/H5 -> 0.090145225 | K5: =G5*(1+Paramètres!$B$11)/(H5+G5*Paramètres!$B$11) -> 0.11321712 | L5: =G5*(1+Paramètres!$B$12)/(H5+G5*Paramètres!$B$12) -> 0.12672208 | M5: =IF(F5>0,(I5-(F5-G5*Paramètres!$B$11)/(E5-G5*Paramètres!$B$11))*100,"n.s.") -> 3.2369996 | N5: =IF(F5>0,(I5-(F5-G5*Paramètres!$B$12)/(E5-G5*Paramètres!$B$12))*100,"n.s.") -> 5.3697283 | O5: =IF(F5>0,G5*Paramètres!$B$11/F5,"n.s.") -> 0.13928144 | P5: =IF(F5>0,G5*Paramètres!$B$12/F5,"n.s.") -> 0.22422351 | Q5: =C5*(Paramètres!$B$5/Paramètres!$B$4)*Paramètres!$B$11/1000 -> 2.5764618 | R5: =C5*(Paramètres!$B$5/Paramètres!$B$4)*Paramètres!$B$12/1000 -> 4.1477406
A6: Transport par eau | B6: =INDEX(Données2019!$D$2:$D$31,MATCH(A6,Données2019!$C$2:$C$31,0)) -> oui | C6: =SUMIFS(Données2019!$E$2:$E$31,Données2019!$C$2:$C$31,$A6) -> 2156.35 | D6: =SUMIFS(Données2019!$F$2:$F$31,Données2019!$C$2:$C$31,$A6) -> 16970 | E6: =SUMIFS(Données2019!$G$2:$G$31,Données2019!$C$2:$C$31,$A6) -> 735.57 | F6: =SUMIFS(Données2019!$H$2:$H$31,Données2019!$C$2:$C$31,$A6) -> -193.43 | G6: =C6*Paramètres!$B$8 -> 2071.3713 | H6: =D6-F6 -> 17163.43 | I6: =F6/E6 -> -0.26296614 | J6: =G6/H6 -> 0.12068516 | K6: =G6*(1+Paramètres!$B$11)/(H6+G6*Paramètres!$B$11) -> 0.15028243 | L6: =G6*(1+Paramètres!$B$12)/(H6+G6*Paramètres!$B$12) -> 0.16737419 | M6: =IF(F6>0,(I6-(F6-G6*Paramètres!$B$11)/(E6-G6*Paramètres!$B$11))*100,"n.s.") -> n.s. | N6: =IF(F6>0,(I6-(F6-G6*Paramètres!$B$12)/(E6-G6*Paramètres!$B$12))*100,"n.s.") -> n.s. | O6: =IF(F6>0,G6*Paramètres!$B$11/F6,"n.s.") -> n.s. | P6: =IF(F6>0,G6*Paramètres!$B$12/F6,"n.s.") -> n.s. | Q6: =C6*(Paramètres!$B$5/Paramètres!$B$4)*Paramètres!$B$11/1000 -> 0.70880023 | R6: =C6*(Paramètres!$B$5/Paramètres!$B$4)*Paramètres!$B$12/1000 -> 1.1410685
A7: Transport aérien | B7: =INDEX(Données2019!$D$2:$D$31,MATCH(A7,Données2019!$C$2:$C$31,0)) -> oui | C7: =SUMIFS(Données2019!$E$2:$E$31,Données2019!$C$2:$C$31,$A7) -> 4933.4 | D7: =SUMIFS(Données2019!$F$2:$F$31,Données2019!$C$2:$C$31,$A7) -> 21133 | E7: =SUMIFS(Données2019!$G$2:$G$31,Données2019!$C$2:$C$31,$A7) -> 7726.46 | F7: =SUMIFS(Données2019!$H$2:$H$31,Données2019!$C$2:$C$31,$A7) -> 2507.46 | G7: =C7*Paramètres!$B$8 -> 4738.9817 | H7: =D7-F7 -> 18625.54 | I7: =F7/E7 -> 0.32452896 | J7: =G7/H7 -> 0.25443459 | K7: =G7*(1+Paramètres!$B$11)/(H7+G7*Paramètres!$B$11) -> 0.30543923 | L7: =G7*(1+Paramètres!$B$12)/(H7+G7*Paramètres!$B$12) -> 0.33325636 | M7: =IF(F7>0,(I7-(F7-G7*Paramètres!$B$11)/(E7-G7*Paramètres!$B$11))*100,"n.s.") -> 14.529354 | N7: =IF(F7>0,(I7-(F7-G7*Paramètres!$B$12)/(E7-G7*Paramètres!$B$12))*100,"n.s.") -> 26.921832 | O7: =IF(F7>0,G7*Paramètres!$B$11/F7,"n.s.") -> 0.54547425 | P7: =IF(F7>0,G7*Paramètres!$B$12/F7,"n.s.") -> 0.87813672 | Q7: =C7*(Paramètres!$B$5/Paramètres!$B$4)*Paramètres!$B$11/1000 -> 1.6216269 | R7: =C7*(Paramètres!$B$5/Paramètres!$B$4)*Paramètres!$B$12/1000 -> 2.6105908
A8: Entreposage et services auxiliaires des transports | B8: =INDEX(Données2019!$D$2:$D$31,MATCH(A8,Données2019!$C$2:$C$31,0)) -> oui | C8: =SUMIFS(Données2019!$E$2:$E$31,Données2019!$C$2:$C$31,$A8) -> 983.37 | D8: =SUMIFS(Données2019!$F$2:$F$31,Données2019!$C$2:$C$31,$A8) -> 74866 | E8: =SUMIFS(Données2019!$G$2:$G$31,Données2019!$C$2:$C$31,$A8) -> 36057.32 | F8: =SUMIFS(Données2019!$H$2:$H$31,Données2019!$C$2:$C$31,$A8) -> 16232.32 | G8: =C8*Paramètres!$B$8 -> 944.61677 | H8: =D8-F8 -> 58633.68 | I8: =F8/E8 -> 0.45018099 | J8: =G8/H8 -> 0.016110481 | K8: =G8*(1+Paramètres!$B$11)/(H8+G8*Paramètres!$B$11) -> 0.02066417 | L8: =G8*(1+Paramètres!$B$12)/(H8+G8*Paramètres!$B$12) -> 0.023420645 | M8: =IF(F8>0,(I8-(F8-G8*Paramètres!$B$11)/(E8-G8*Paramètres!$B$11))*100,"n.s.") -> 0.41889138 | N8: =IF(F8>0,(I8-(F8-G8*Paramètres!$B$12)/(E8-G8*Paramètres!$B$12))*100,"n.s.") -> 0.67750404 | O8: =IF(F8>0,G8*Paramètres!$B$11/F8,"n.s.") -> 0.016795707 | P8: =IF(F8>0,G8*Paramètres!$B$12/F8,"n.s.") -> 0.027038723 | Q8: =C8*(Paramètres!$B$5/Paramètres!$B$4)*Paramètres!$B$11/1000 -> 0.32323736 | R8: =C8*(Paramètres!$B$5/Paramètres!$B$4)*Paramètres!$B$12/1000 -> 0.52036662
A9: Poste et courrier | B9: =INDEX(Données2019!$D$2:$D$31,MATCH(A9,Données2019!$C$2:$C$31,0)) -> oui | C9: =SUMIFS(Données2019!$E$2:$E$31,Données2019!$C$2:$C$31,$A9) -> 100.64 | D9: =SUMIFS(Données2019!$F$2:$F$31,Données2019!$C$2:$C$31,$A9) -> 12395 | E9: =SUMIFS(Données2019!$G$2:$G$31,Données2019!$C$2:$C$31,$A9) -> 7777.25 | F9: =SUMIFS(Données2019!$H$2:$H$31,Données2019!$C$2:$C$31,$A9) -> 346.25 | G9: =C9*Paramètres!$B$8 -> 96.673919 | H9: =D9-F9 -> 12048.75 | I9: =F9/E9 -> 0.044520878 | J9: =G9/H9 -> 0.0080235642 | K9: =G9*(1+Paramètres!$B$11)/(H9+G9*Paramètres!$B$11) -> 0.01031542 | L9: =G9*(1+Paramètres!$B$12)/(H9+G9*Paramètres!$B$12) -> 0.011707939 | M9: =IF(F9>0,(I9-(F9-G9*Paramètres!$B$11)/(E9-G9*Paramètres!$B$11))*100,"n.s.") -> 0.34402388 | N9: =IF(F9>0,(I9-(F9-G9*Paramètres!$B$12)/(E9-G9*Paramètres!$B$12))*100,"n.s.") -> 0.55504879 | O9: =IF(F9>0,G9*Paramètres!$B$11/F9,"n.s.") -> 0.08058288 | P9: =IF(F9>0,G9*Paramètres!$B$12/F9,"n.s.") -> 0.12972709 | Q9: =C9*(Paramètres!$B$5/Paramètres!$B$4)*Paramètres!$B$11/1000 -> 0.033080741 | R9: =C9*(Paramètres!$B$5/Paramètres!$B$4)*Paramètres!$B$12/1000 -> 0.053255333
A10: Commerce et réparation automobile | B10: =INDEX(Données2019!$D$2:$D$31,MATCH(A10,Données2019!$C$2:$C$31,0)) -> non | C10: =SUMIFS(Données2019!$E$2:$E$31,Données2019!$C$2:$C$31,$A10) -> 346.54 | D10: =SUMIFS(Données2019!$F$2:$F$31,Données2019!$C$2:$C$31,$A10) -> 56242 | E10: =SUMIFS(Données2019!$G$2:$G$31,Données2019!$C$2:$C$31,$A10) -> 33194.78 | F10: =SUMIFS(Données2019!$H$2:$H$31,Données2019!$C$2:$C$31,$A10) -> 11328.78 | G10: =C10*Paramètres!$B$8 -> 332.88335 | H10: =D10-F10 -> 44913.22 | I10: =F10/E10 -> 0.34128197 | J10: =G10/H10 -> 0.0074117008 | K10: =G10*(1+Paramètres!$B$11)/(H10+G10*Paramètres!$B$11) -> 0.0095304631 | L10: =G10*(1+Paramètres!$B$12)/(H10+G10*Paramètres!$B$12) -> 0.010818175 | M10: =IF(F10>0,(I10-(F10-G10*Paramètres!$B$11)/(E10-G10*Paramètres!$B$11))*100,"n.s.") -> 0.19120704 | N10: =IF(F10>0,(I10-(F10-G10*Paramètres!$B$12)/(E10-G10*Paramètres!$B$12))*100,"n.s.") -> 0.30836228 | O10: =IF(F10>0,G10*Paramètres!$B$11/F10,"n.s.") -> 0.0084807091 | P10: =IF(F10>0,G10*Paramètres!$B$12/F10,"n.s.") -> 0.013652747 | Q10: =C10*(Paramètres!$B$5/Paramètres!$B$4)*Paramètres!$B$11/1000 -> 0.11390898 | R10: =C10*(Paramètres!$B$5/Paramètres!$B$4)*Paramètres!$B$12/1000 -> 0.18337742
A11: Commerce de gros | B11: =INDEX(Données2019!$D$2:$D$31,MATCH(A11,Données2019!$C$2:$C$31,0)) -> non | C11: =SUMIFS(Données2019!$E$2:$E$31,Données2019!$C$2:$C$31,$A11) -> 3856.45 | D11: =SUMIFS(Données2019!$F$2:$F$31,Données2019!$C$2:$C$31,$A11) -> 238341 | E11: =SUMIFS(Données2019!$G$2:$G$31,Données2019!$C$2:$C$31,$A11) -> 102182.45 | F11: =SUMIFS(Données2019!$H$2:$H$31,Données2019!$C$2:$C$31,$A11) -> 37493.45 | G11: =C11*Paramètres!$B$8 -> 3704.4727 | H11: =D11-F11 -> 200847.55 | I11: =F11/E11 -> 0.36692651 | J11: =G11/H11 -> 0.018444202 | K11: =G11*(1+Paramètres!$B$11)/(H11+G11*Paramètres!$B$11) -> 0.023641676 | L11: =G11*(1+Paramètres!$B$12)/(H11+G11*Paramètres!$B$12) -> 0.02678447 | M11: =IF(F11>0,(I11-(F11-G11*Paramètres!$B$11)/(E11-G11*Paramètres!$B$11))*100,"n.s.") -> 0.66941525 | N11: =IF(F11>0,(I11-(F11-G11*Paramètres!$B$12)/(E11-G11*Paramètres!$B$12))*100,"n.s.") -> 1.0846589 | O11: =IF(F11>0,G11*Paramètres!$B$11/F11,"n.s.") -> 0.02851637 | P11: =IF(F11>0,G11*Paramètres!$B$12/F11,"n.s.") -> 0.045907339 | Q11: =C11*(Paramètres!$B$5/Paramètres!$B$4)*Paramètres!$B$11/1000 -> 1.2676294 | R11: =C11*(Paramètres!$B$5/Paramètres!$B$4)*Paramètres!$B$12/1000 -> 2.0407048
A12: Commerce de détail | B12: =INDEX(Données2019!$D$2:$D$31,MATCH(A12,Données2019!$C$2:$C$31,0)) -> non | C12: =SUMIFS(Données2019!$E$2:$E$31,Données2019!$C$2:$C$31,$A12) -> 1309.57 | D12: =SUMIFS(Données2019!$F$2:$F$31,Données2019!$C$2:$C$31,$A12) -> 161294.17 | E12: =SUMIFS(Données2019!$G$2:$G$31,Données2019!$C$2:$C$31,$A12) -> 89566.63 | F12: =SUMIFS(Données2019!$H$2:$H$31,Données2019!$C$2:$C$31,$A12) -> 26883.63 | G12: =C12*Paramètres!$B$8 -> 1257.9617 | H12: =D12-F12 -> 134410.54 | I12: =F12/E12 -> 0.3001523 | J12: =G12/H12 -> 0.0093591 | K12: =G12*(1+Paramètres!$B$11)/(H12+G12*Paramètres!$B$11) -> 0.012027814 | L12: =G12*(1+Paramètres!$B$12)/(H12+G12*Paramètres!$B$12) -> 0.013648307 | M12: =IF(F12>0,(I12-(F12-G12*Paramètres!$B$11)/(E12-G12*Paramètres!$B$11))*100,"n.s.") -> 0.28484724 | N12: =IF(F12>0,(I12-(F12-G12*Paramètres!$B$12)/(E12-G12*Paramètres!$B$12))*100,"n.s.") -> 0.45970502 | O12: =IF(F12>0,G12*Paramètres!$B$11/F12,"n.s.") -> 0.013505254 | P12: =IF(F12>0,G12*Paramètres!$B$12/F12,"n.s.") -> 0.021741556 | Q12: =C12*(Paramètres!$B$5/Paramètres!$B$4)*Paramètres!$B$11/1000 -> 0.43046051 | R12: =C12*(Paramètres!$B$5/Paramètres!$B$4)*Paramètres!$B$12/1000 -> 0.69298079
A13: Hébergement-restauration | B13: =INDEX(Données2019!$D$2:$D$31,MATCH(A13,Données2019!$C$2:$C$31,0)) -> non | C13: =SUMIFS(Données2019!$E$2:$E$31,Données2019!$C$2:$C$31,$A13) -> 240.19 | D13: =SUMIFS(Données2019!$F$2:$F$31,Données2019!$C$2:$C$31,$A13) -> 121745 | E13: =SUMIFS(Données2019!$G$2:$G$31,Données2019!$C$2:$C$31,$A13) -> 63075.15 | F13: =SUMIFS(Données2019!$H$2:$H$31,Données2019!$C$2:$C$31,$A13) -> 23226.15 | G13: =C13*Paramètres!$B$8 -> 230.72445 | H13: =D13-F13 -> 98518.85 | I13: =F13/E13 -> 0.3682298 | J13: =G13/H13 -> 0.002341932 | K13: =G13*(1+Paramètres!$B$11)/(H13+G13*Paramètres!$B$11) -> 0.003015817 | L13: =G13*(1+Paramètres!$B$12)/(H13+G13*Paramètres!$B$12) -> 0.0034263453 | M13: =IF(F13>0,(I13-(F13-G13*Paramètres!$B$11)/(E13-G13*Paramètres!$B$11))*100,"n.s.") -> 0.066769243 | N13: =IF(F13>0,(I13-(F13-G13*Paramètres!$B$12)/(E13-G13*Paramètres!$B$12))*100,"n.s.") -> 0.1075584 | O13: =IF(F13>0,G13*Paramètres!$B$11/F13,"n.s.") -> 0.0028670788 | P13: =IF(F13>0,G13*Paramètres!$B$12/F13,"n.s.") -> 0.0046155931 | Q13: =C13*(Paramètres!$B$5/Paramètres!$B$4)*Paramètres!$B$11/1000 -> 0.078951343 | R13: =C13*(Paramètres!$B$5/Paramètres!$B$4)*Paramètres!$B$12/1000 -> 0.12710054
A14: Information-communication | B14: =INDEX(Données2019!$D$2:$D$31,MATCH(A14,Données2019!$C$2:$C$31,0)) -> non | C14: =SUMIFS(Données2019!$E$2:$E$31,Données2019!$C$2:$C$31,$A14) -> 1243.23 | D14: =SUMIFS(Données2019!$F$2:$F$31,Données2019!$C$2:$C$31,$A14) -> 223402 | E14: =SUMIFS(Données2019!$G$2:$G$31,Données2019!$C$2:$C$31,$A14) -> 116240.17 | F14: =SUMIFS(Données2019!$H$2:$H$31,Données2019!$C$2:$C$31,$A14) -> 45162.17 | G14: =C14*Paramètres!$B$8 -> 1194.2361 | H14: =D14-F14 -> 178239.83 | I14: =F14/E14 -> 0.38852464 | J14: =G14/H14 -> 0.0067001638 | K14: =G14*(1+Paramètres!$B$11)/(H14+G14*Paramètres!$B$11) -> 0.0086172869 | L14: =G14*(1+Paramètres!$B$12)/(H14+G14*Paramètres!$B$12) -> 0.0097828335 | M14: =IF(F14>0,(I14-(F14-G14*Paramètres!$B$11)/(E14-G14*Paramètres!$B$11))*100,"n.s.") -> 0.18185525 | N14: =IF(F14>0,(I14-(F14-G14*Paramètres!$B$12)/(E14-G14*Paramètres!$B$12))*100,"n.s.") -> 0.2932933 | O14: =IF(F14>0,G14*Paramètres!$B$11/F14,"n.s.") -> 0.0076320045 | P14: =IF(F14>0,G14*Paramètres!$B$12/F14,"n.s.") -> 0.012286452 | Q14: =C14*(Paramètres!$B$5/Paramètres!$B$4)*Paramètres!$B$11/1000 -> 0.40865431 | R14: =C14*(Paramètres!$B$5/Paramètres!$B$4)*Paramètres!$B$12/1000 -> 0.65787587
A15: Finance-assurance | B15: =INDEX(Données2019!$D$2:$D$31,MATCH(A15,Données2019!$C$2:$C$31,0)) -> non | C15: =SUMIFS(Données2019!$E$2:$E$31,Données2019!$C$2:$C$31,$A15) -> 598.89 | D15: =SUMIFS(Données2019!$F$2:$F$31,Données2019!$C$2:$C$31,$A15) -> 235135 | E15: =SUMIFS(Données2019!$G$2:$G$31,Données2019!$C$2:$C$31,$A15) -> 83195.7 | F15: =SUMIFS(Données2019!$H$2:$H$31,Données2019!$C$2:$C$31,$A15) -> 19764.7 | G15: =C15*Paramètres!$B$8 -> 575.28859 | H15: =D15-F15 -> 215370.3 | I15: =F15/E15 -> 0.23756877 | J15: =G15/H15 -> 0.0026711603 | K15: =G15*(1+Paramètres!$B$11)/(H15+G15*Paramètres!$B$11) -> 0.0034394533 | L15: =G15*(1+Paramètres!$B$12)/(H15+G15*Paramètres!$B$12) -> 0.003907423 | M15: =IF(F15>0,(I15-(F15-G15*Paramètres!$B$11)/(E15-G15*Paramètres!$B$11))*100,"n.s.") -> 0.1524672 | N15: =IF(F15>0,(I15-(F15-G15*Paramètres!$B$12)/(E15-G15*Paramètres!$B$12))*100,"n.s.") -> 0.24575042 | O15: =IF(F15>0,G15*Paramètres!$B$11/F15,"n.s.") -> 0.0084007638 | P15: =IF(F15>0,G15*Paramètres!$B$12/F15,"n.s.") -> 0.013524047 | Q15: =C15*(Paramètres!$B$5/Paramètres!$B$4)*Paramètres!$B$11/1000 -> 0.19685736 | R15: =C15*(Paramètres!$B$5/Paramètres!$B$4)*Paramètres!$B$12/1000 -> 0.31691263
A16: Immobilier (hors loyers imputés) | B16: =INDEX(Données2019!$D$2:$D$31,MATCH(A16,Données2019!$C$2:$C$31,0)) -> non | C16: =SUMIFS(Données2019!$E$2:$E$31,Données2019!$C$2:$C$31,$A16) -> 157.24 | D16: =SUMIFS(Données2019!$F$2:$F$31,Données2019!$C$2:$C$31,$A16) -> 152352 | E16: =SUMIFS(Données2019!$G$2:$G$31,Données2019!$C$2:$C$31,$A16) -> 106626.25 | F16: =SUMIFS(Données2019!$H$2:$H$31,Données2019!$C$2:$C$31,$A16) -> 77007.5 | G16: =C16*Paramètres!$B$8 -> 151.04339 | H16: =D16-F16 -> 75344.5 | I16: =F16/E16 -> 0.72221897 | J16: =G16/H16 -> 0.0020047036 | K16: =G16*(1+Paramètres!$B$11)/(H16+G16*Paramètres!$B$11) -> 0.0025818031 | L16: =G16*(1+Paramètres!$B$12)/(H16+G16*Paramètres!$B$12) -> 0.002933425 | M16: =IF(F16>0,(I16-(F16-G16*Paramètres!$B$11)/(E16-G16*Paramètres!$B$11))*100,"n.s.") -> 0.01136164 | N16: =IF(F16>0,(I16-(F16-G16*Paramètres!$B$12)/(E16-G16*Paramètres!$B$12))*100,"n.s.") -> 0.018295204 | O16: =IF(F16>0,G16*Paramètres!$B$11/F16,"n.s.") -> 0.00056609843 | P16: =IF(F16>0,G16*Paramètres!$B$12/F16,"n.s.") -> 0.00091133874 | Q16: =C16*(Paramètres!$B$5/Paramètres!$B$4)*Paramètres!$B$11/1000 -> 0.05168537 | R16: =C16*(Paramètres!$B$5/Paramètres!$B$4)*Paramètres!$B$12/1000 -> 0.083206167
... A21: Autres services aux ménages | B21: =INDEX(Données2019!$D$2:$D$31,MATCH(A21,Données2019!$C$2:$C$31,0)) -> non | C21: =SUMIFS(Données2019!$E$2:$E$31,Données2019!$C$2:$C$31,$A21) -> 120.89 | D21: =SUMIFS(Données2019!$F$2:$F$31,Données2019!$C$2:$C$31,$A21) -> 28606 | E21: =SUMIFS(Données2019!$G$2:$G$31,Données2019!$C$2:$C$31,$A21) -> 17470.66 | F21: =SUMIFS(Données2019!$H$2:$H$31,Données2019!$C$2:$C$31,$A21) -> 7650.66 | G21: =C21*Paramètres!$B$8 -> 116.1259 | H21: =D21-F21 -> 20955.34 | I21: =F21/E21 -> 0.43791477 | J21: =G21/H21 -> 0.0055415897 | K21: =G21*(1+Paramètres!$B$11)/(H21+G21*Paramètres!$B$11) -> 0.0071295885 | L21: =G21*(1+Paramètres!$B$12)/(H21+G21*Paramètres!$B$12) -> 0.0080955569 | M21: =IF(F21>0,(I21-(F21-G21*Paramètres!$B$11)/(E21-G21*Paramètres!$B$11))*100,"n.s.") -> 0.10803865 | N21: =IF(F21>0,(I21-(F21-G21*Paramètres!$B$12)/(E21-G21*Paramètres!$B$12))*100,"n.s.") -> 0.17413112 | O21: =IF(F21>0,G21*Paramètres!$B$11/F21,"n.s.") -> 0.0043807999 | P21: =IF(F21>0,G21*Paramètres!$B$12/F21,"n.s.") -> 0.0070524708 | Q21: =C21*(Paramètres!$B$5/Paramètres!$B$4)*Paramètres!$B$11/1000 -> 0.039736991 | R21: =C21*(Paramètres!$B$5/Paramètres!$B$4)*Paramètres!$B$12/1000 -> 0.063970958
A22: TOTAL tertiaire marchand | B22: tous | C22: =SUM(C5:C21) -> 27929.11 | D22: =SUM(D5:D21) -> 2100526.2 | E22: =SUM(E5:E21) -> 1049035.4 | F22: =SUM(F5:F21) -> 383891.64 | G22: =C22*Paramètres!$B$8 -> 26828.463 | H22: =D22-F22 -> 1716634.5 | I22: =F22/E22 -> 0.36594727 | J22: =G22/H22 -> 0.015628524 | K22: =G22*(1+Paramètres!$B$11)/(H22+G22*Paramètres!$B$11) -> 0.020048762 | L22: =G22*(1+Paramètres!$B$12)/(H22+G22*Paramètres!$B$12) -> 0.02272505 | M22: =IF(F22>0,(I22-(F22-G22*Paramètres!$B$11)/(E22-G22*Paramètres!$B$11))*100,"n.s.") -> 0.47148924 | N22: =IF(F22>0,(I22-(F22-G22*Paramètres!$B$12)/(E22-G22*Paramètres!$B$12))*100,"n.s.") -> 0.76248915 | O22: =IF(F22>0,G22*Paramètres!$B$11/F22,"n.s.") -> 0.020170208 | P22: =IF(F22>0,G22*Paramètres!$B$12/F22,"n.s.") -> 0.032471194 | Q22: =C22*(Paramètres!$B$5/Paramètres!$B$4)*Paramètres!$B$11/1000 -> 9.1804019 | R22: =C22*(Paramètres!$B$5/Paramètres!$B$4)*Paramètres!$B$12/1000 -> 14.779154
A23: TOTAL hors transport | B23: non | C23: =SUMIFS(C$5:C$21,$B$5:$B$21,"non") -> 11917.1 | D23: =SUMIFS(D$5:D$21,$B$5:$B$21,"non") -> 1876035.2 | E23: =SUMIFS(E$5:E$21,$B$5:$B$21,"non") -> 949699.52 | F23: =SUMIFS(F$5:F$21,$B$5:$B$21,"non") -> 349396.77 | G23: =C23*Paramètres!$B$8 -> 11447.464 | H23: =D23-F23 -> 1526638.4 | I23: =F23/E23 -> 0.36790244 | J23: =G23/H23 -> 0.0074984776 | K23: =G23*(1+Paramètres!$B$11)/(H23+G23*Paramètres!$B$11) -> 0.0096418056 | L23: =G23*(1+Paramètres!$B$12)/(H23+G23*Paramètres!$B$12) -> 0.010944396 | M23: =IF(F23>0,(I23-(F23-G23*Paramètres!$B$11)/(E23-G23*Paramètres!$B$11))*100,"n.s.") -> 0.22067033 | N23: =IF(F23>0,(I23-(F23-G23*Paramètres!$B$12)/(E23-G23*Paramètres!$B$12))*100,"n.s.") -> 0.3560061 | O23: =IF(F23>0,G23*Paramètres!$B$11/F23,"n.s.") -> 0.0094561344 | P23: =IF(F23>0,G23*Paramètres!$B$12/F23,"n.s.") -> 0.015223045 | Q23: =C23*(Paramètres!$B$5/Paramètres!$B$4)*Paramètres!$B$11/1000 -> 3.9171949 | R23: =C23*(Paramètres!$B$5/Paramètres!$B$4)*Paramètres!$B$12/1000 -> 6.3061321
A24: TOTAL transport et entreposage | B24: oui | C24: =SUMIFS(C$5:C$21,$B$5:$B$21,"oui") -> 16012.01 | D24: =SUMIFS(D$5:D$21,$B$5:$B$21,"oui") -> 224491 | E24: =SUMIFS(E$5:E$21,$B$5:$B$21,"oui") -> 99335.87 | F24: =SUMIFS(F$5:F$21,$B$5:$B$21,"oui") -> 34494.87 | G24: =C24*Paramètres!$B$8 -> 15380.999 | H24: =D24-F24 -> 189996.13 | I24: =F24/E24 -> 0.34725492 | J24: =G24/H24 -> 0.080954276 | K24: =G24*(1+Paramètres!$B$11)/(H24+G24*Paramètres!$B$11) -> 0.10193738 | L24: =G24*(1+Paramètres!$B$12)/(H24+G24*Paramètres!$B$12) -> 0.11427022 | M24: =IF(F24>0,(I24-(F24-G24*Paramètres!$B$11)/(E24-G24*Paramètres!$B$11))*100,"n.s.") -> 3.0535186 | N24: =IF(F24>0,(I24-(F24-G24*Paramètres!$B$12)/(E24-G24*Paramètres!$B$12))*100,"n.s.") -> 5.0600943 | O24: =IF(F24>0,G24*Paramètres!$B$11/F24,"n.s.") -> 0.12869251 | P24: =IF(F24>0,G24*Paramètres!$B$12/F24,"n.s.") -> 0.20717682 | Q24: =C24*(Paramètres!$B$5/Paramètres!$B$4)*Paramètres!$B$11/1000 -> 5.263207 | R24: =C24*(Paramètres!$B$5/Paramètres!$B$4)*Paramètres!$B$12/1000 -> 8.473022
A26: n.s. : non significatif (EBE négatif en 2019). Surcoût en euros : ordre de grandeur à volumes 2019 et prix 2025.

Sheet Prix
A1: Mois | B1: Gazole (€/L TTC) | C1: SP95-E10 (€/L TTC)
A2: 2022-01 | B2: 1.63 | C2: 1.69
A3: 2022-02 | B3: 1.72 | C3: 1.77
A4: 2022-03 | B4: 2.02 | C4: 1.96
A5: 2022-04 | B5: 1.87 | C5: 1.76
A6: 2022-05 | B6: 1.9 | C6: 1.89
A7: 2022-06 | B7: 2.09 | C7: 2.08
A8: 2022-07 | B8: 2 | C8: 1.95
A9: 2022-08 | B9: 1.87 | C9: 1.77
A10: 2022-09 | B10: 1.74 | C10: 1.51
A11: 2022-10 | B11: 1.87 | C11: 1.62
A12: 2022-11 | B12: 1.88 | C12: 1.68
A13: 2022-12 | B13: 1.78 | C13: 1.65
... A57: 2026-08 | B57: 2.21 | C57: 2.01
A59: Source : INSEE, prix moyens mensuels de vente au détail en métropole, séries 000442588 (gazole) et 010596132 (SP95-E10).
